softkeyboard/__init__.py
softkeyboard/default_layout.json
softkeyboard/default_layout.json.license
softkeyboard/mobile_layout.json
softkeyboard/mobile_layout.json.license
softkeyboard/softkeyboard.py
circuitpython_softkeyboard-1.0.0.dist-info/LICENSE
circuitpython_softkeyboard-1.0.0.dist-info/METADATA
circuitpython_softkeyboard-1.0.0.dist-info/WHEEL
circuitpython_softkeyboard-1.0.0.dist-info/top_level.txt
circuitpython_softkeyboard-1.0.0.dist-info/RECORD
