Metadata-Version: 2.1
Name: circuitpython-softkeyboard
Version: 1.0.0
Summary: CircuitPython software defined keyboard for touch displays using displayio GridLayout.
Author-email: "Tim Cocks, DJDevon3" <foamyguy@gmail.com>
License: MIT
Project-URL: Homepage, https://github.com/Foamyguy/CircuitPython_SoftKeyboard
Keywords: adafruit,blinka,circuitpython,micropython,softkeyboard,keyboard,softkeyboard,touchscreen,displayio,display,ui,gui,qwerty
Classifier: Intended Audience :: Developers
Classifier: Topic :: Software Development :: Libraries
Classifier: Topic :: Software Development :: Embedded Systems
Classifier: Topic :: System :: Hardware
Classifier: License :: OSI Approved :: MIT License
Classifier: Programming Language :: Python :: 3
License-File: LICENSE
Requires-Dist: Adafruit-Blinka
Requires-Dist: adafruit-circuitpython-bitmap-font
Requires-Dist: adafruit-circuitpython-display-text
Requires-Dist: adafruit-circuitpython-displayio-layout
Provides-Extra: optional
